{
  "id": 1117724,
  "organo": {
    "nivel1": "AUTONOMICA",
    "nivel2": "REGIÓN DE MURCIA",
    "nivel3": "INSTITUTO DE FOMENTO DE LA REGIÓN DE MURCIA (INFO)"
  },
  "sedeElectronica": "https://sede.institutofomentomurcia.es/infodirecto",
  "codigoBDNS": "916163",
  "fechaRecepcion": "2026-06-30",
  "instrumentos": [
    {
      "descripcion": "SUBVENCIÓN Y ENTREGA DINERARIA SIN CONTRAPRESTACIÓN "
    }
  ],
  "tipoConvocatoria": "Concurrencia competitiva - canónica",
  "presupuestoTotal": 3000000,
  "mrr": false,
  "descripcion": "Extracto de la Resolución de 17 de junio de 2026, del Director del Instituto de Fomento de la Región de Murcia,  de la convocatoria de tramitación anticipada de ayudas destinadas a fomentar la I+D empresarial en el marco de la Estrategia RIS4 R. de Murcia",
  "descripcionLeng": null,
  "tiposBeneficiarios": [
    {
      "descripcion": "GRAN EMPRESA"
    },
    {
      "descripcion": "PYME Y PERSONAS FÍSICAS QUE DESARROLLAN ACTIVIDAD ECONÓMICA"
    }
  ],
  "sectores": [
    {
      "descripcion": "Acabado de textiles",
      "codigo": "13.3"
    },
    {
      "descripcion": "Actividades administrativas y auxiliares de oficina",
      "codigo": "82.1"
    },
    {
      "descripcion": "Actividades de agencias de viajes, operadores turísticos, servicios de reservas y actividades relacionadas ",
      "codigo": "79"
    },
    {
      "descripcion": "Actividades de bibliotecas, archivos, museos y otras actividades culturales",
      "codigo": "91"
    },
    {
      "descripcion": "Actividades de construcción especializada",
      "codigo": "43"
    },
    {
      "descripcion": "Actividades de creación artística y artes escénicas",
      "codigo": "90"
    },
    {
      "descripcion": "Actividades de descontaminación y otros servicios de gestión de residuos",
      "codigo": "39"
    },
    {
      "descripcion": "Actividades de los centros de llamadas",
      "codigo": "82.2"
    },
    {
      "descripcion": "Actividades de programación, radiodifusión, agencias de noticias y otras actividades de distribución de contenidos",
      "codigo": "60"
    },
    {
      "descripcion": "Actividades de publicidad, estudios de mercado y relaciones públicas ",
      "codigo": "73"
    },
    {
      "descripcion": "Actividades de recogida, tratamiento y eliminación de residuos ",
      "codigo": "38"
    },
    {
      "descripcion": "Actividades de servicios sociales sin alojamiento",
      "codigo": "88"
    },
    {
      "descripcion": "Actividades deportivas, recreativas y de entretenimiento",
      "codigo": "93"
    },
    {
      "descripcion": "Actividades jurídicas y de contabilidad",
      "codigo": "69"
    },
    {
      "descripcion": "Actividades sanitarias",
      "codigo": "86"
    },
    {
      "descripcion": "AGRICULTURA, GANADERÍA, SILVICULTURA Y PESCA",
      "codigo": "A"
    },
    {
      "descripcion": "Alquiler de otra maquinaria, equipos y bienes tangibles",
      "codigo": "77.3"
    },
    {
      "descripcion": "Alquiler de vehículos de motor",
      "codigo": "77.1"
    },
    {
      "descripcion": "Arrendamiento de la propiedad intelectual y productos similares, excepto obras protegidas por derechos de autor",
      "codigo": "77.4"
    },
    {
      "descripcion": "Artes gráficas y reproducción de soportes grabados",
      "codigo": "18"
    },
    {
      "descripcion": "Asistencia en establecimientos residenciales",
      "codigo": "87"
    },
    {
      "descripcion": "Captación, depuración y distribución de agua",
      "codigo": "36"
    },
    {
      "descripcion": "Confección de prendas de vestir",
      "codigo": "14"
    },
    {
      "descripcion": "Construcción de edificios",
      "codigo": "41"
    },
    {
      "descripcion": "Construcción naval",
      "codigo": "30.1"
    },
    {
      "descripcion": "Depósito, almacenamiento y actividades auxiliares del transporte ",
      "codigo": "52"
    },
    {
      "descripcion": "Edición de programas informáticos",
      "codigo": "58.2"
    },
    {
      "descripcion": "Fabricación de artículos de deporte",
      "codigo": "32.3"
    },
    {
      "descripcion": "Fabricación de bebidas",
      "codigo": "11"
    },
    {
      "descripcion": "Fabricación de carrocerías para vehículos de motor; fabricación de remolques y semirremolques",
      "codigo": "29.2"
    },
    {
      "descripcion": "Fabricación de cisternas, grandes depósitos y contenedores de metal",
      "codigo": "25.2"
    },
    {
      "descripcion": "Fabricación de elementos metálicos para la construcción",
      "codigo": "25.1"
    },
    {
      "descripcion": "Fabricación de instrumentos y suministros médicos y odontológicos",
      "codigo": "32.5"
    },
    {
      "descripcion": "Fabricación de juegos y juguetes",
      "codigo": "32.4"
    },
    {
      "descripcion": "Fabricación de maquinaria y equipo n.c.o.p.",
      "codigo": "28"
    },
    {
      "descripcion": "Fabricación de material y equipo eléctrico",
      "codigo": "27"
    },
    {
      "descripcion": "Fabricación de muebles",
      "codigo": "31"
    },
    {
      "descripcion": "Fabricación de otros productos metálicos",
      "codigo": "25.9"
    },
    {
      "descripcion": "Fabricación de otros productos minerales no metálicos",
      "codigo": "23"
    },
    {
      "descripcion": "Fabricación de otros productos textiles",
      "codigo": "13.9"
    },
    {
      "descripcion": "Fabricación de productos básicos de hierro, acero y ferroaleaciones",
      "codigo": "24.1"
    },
    {
      "descripcion": "Fabricación de productos de caucho y plásticos",
      "codigo": "22"
    },
    {
      "descripcion": "Fabricación de productos farmacéuticos",
      "codigo": "21"
    },
    {
      "descripcion": "Fabricación de productos informáticos, electrónicos y ópticos",
      "codigo": "26"
    },
    {
      "descripcion": "Fabricación de tejidos textiles",
      "codigo": "13.2"
    },
    {
      "descripcion": "Fabricación de tubos, tuberías, perfiles huecos y sus accesorios, de acero",
      "codigo": "24.2"
    },
    {
      "descripcion": "Industria alimentaria",
      "codigo": "10"
    },
    {
      "descripcion": "Industria de la madera y del corcho, excepto muebles; cestería y espartería",
      "codigo": "16"
    },
    {
      "descripcion": "Industria del cuero y productos relacionados de otros materiales",
      "codigo": "15"
    },
    {
      "descripcion": "Industria del papel",
      "codigo": "17"
    },
    {
      "descripcion": "Industria química",
      "codigo": "20"
    },
    {
      "descripcion": "Industrias manufactureras n.c.o.p.",
      "codigo": "32.9"
    },
    {
      "descripcion": "Infraestructura informática, tratamiento de datos, alojamiento de datos y otras actividades de servicios de información",
      "codigo": "63"
    },
    {
      "descripcion": "Ingeniería civil",
      "codigo": "42"
    },
    {
      "descripcion": "Investigación y desarrollo",
      "codigo": "72"
    },
    {
      "descripcion": "Organización de convenciones y ferias de muestras",
      "codigo": "82.3"
    },
    {
      "descripcion": "Otras actividades de apoyo a las empresas n.c.o.p.",
      "codigo": "82.9"
    },
    {
      "descripcion": "Otras actividades profesionales, científicas y técnicas",
      "codigo": "74"
    },
    {
      "descripcion": "Preparación e hilado de fibras textiles",
      "codigo": "13.1"
    },
    {
      "descripcion": "Producción cinematográfica, de vídeo y de programas de televisión, grabación de sonido y edición musical",
      "codigo": "59"
    },
    {
      "descripcion": "Programación, consultoría y otras actividades relacionadas con la informática",
      "codigo": "62"
    },
    {
      "descripcion": "Recogida y tratamiento de aguas residuales",
      "codigo": "37"
    },
    {
      "descripcion": "Reparación, mantenimiento e instalación de maquinaria y equipos",
      "codigo": "33"
    },
    {
      "descripcion": "Reparación y mantenimiento de ordenadores y equipos de comunicación",
      "codigo": "95.1"
    },
    {
      "descripcion": "Servicios a edificios y actividades de jardinería",
      "codigo": "81"
    },
    {
      "descripcion": "Servicios de alojamiento",
      "codigo": "55"
    },
    {
      "descripcion": "Servicios de comidas y bebidas",
      "codigo": "56"
    },
    {
      "descripcion": "Servicios de investigación y seguridad",
      "codigo": "80"
    },
    {
      "descripcion": "Servicios técnicos de arquitectura e ingeniería; ensayos y análisis técnicos",
      "codigo": "71"
    },
    {
      "descripcion": "Suministro de energía eléctrica, gas, vapor y aire acondicionado",
      "codigo": "35"
    },
    {
      "descripcion": "Telecomunicaciones",
      "codigo": "61"
    },
    {
      "descripcion": "Transporte aéreo",
      "codigo": "51"
    },
    {
      "descripcion": "Transporte marítimo y por vías navegables interiores",
      "codigo": "50"
    },
    {
      "descripcion": "Transporte terrestre y por tubería",
      "codigo": "49"
    },
    {
      "descripcion": "Tratamiento, revestimiento y mecanizado de metales",
      "codigo": "25.5"
    }
  ],
  "regiones": [
    {
      "descripcion": "ES620 - Murcia"
    }
  ],
  "descripcionFinalidad": "Investigación, desarrollo e innovación",
  "descripcionBasesReguladoras": "Orden de 16 de enero de 2024 por la que se aprueban las Bases Reguladoras destinadas a fomentar la I+D empresarial en el marco de la Estrategia RIS4, modificada por orden de 25 de abril de 2026.",
  "urlBasesReguladoras": "https://borm.es/services/anuncio/ano/2026/numero/1821/pdf?id=842503",
  "sePublicaDiarioOficial": true,
  "abierto": false,
  "fechaInicioSolicitud": null,
  "fechaFinSolicitud": null,
  "textInicio": "Desde las 9 horas del día siguiente de la publicación del extracto en el BORM.",
  "textFin": "Hasta las 14:00 del 18 de septiembre de 2026.",
  "ayudaEstado": "SA.00000",
  "urlAyudaEstado": "https://competition-cases.ec.europa.eu/cases/SA.00000",
  "fondos": [
    {
      "descripcion": "FEDER - FONDO EUROPEO DE DESARROLLO REGIONAL"
    }
  ],
  "reglamento": {
    "descripcion": "REG (UE) 651/2014, DE 17 DE JUNIO, de exención de notificación",
    "orden": null
  },
  "objetivos": [
    {
      "descripcion": "ART. 25 AYUDAS A PROYECTOS DE INVESTIGACIÓN Y DESARROLLO."
    }
  ],
  "sectoresProductos": [],
  "documentos": [
    {
      "id": 1484300,
      "descripcion": "BB.RR.",
      "nombreFic": "BBRR.pdf",
      "long": 616808,
      "datMod": "2026-06-30",
      "datPublicacion": "2026-06-30"
    },
    {
      "id": 1484299,
      "descripcion": "Documento de la convocatoria en español",
      "nombreFic": "Convocatoria 2026_v3.copia.pdf",
      "long": 173061,
      "datMod": "2026-06-30",
      "datPublicacion": "2026-06-30"
    }
  ],
  "anuncios": [],
  "advertencia": "La reutilización de los datos del Sistema Nacional de Publicidad de Subvenciones y Ayudas Públicas está sujeta a una serie de restricciones y consideraciones legales. Consulte el aviso legal en https://www.infosubvenciones.es/bdnstrans/GE/es/avisolegal.Además, el usuario debe ser consciente que la información presentada es de naturaleza dinámica, y que los datos pueden ser sometidos a correcciones, inserciones, modificaciones y eliminaciones en momentos posteriores a su extracción. Accesos al API del sistema Nacional de Publicidad de Subvenciones y Ayudas Públicas. La Administración Presupuestaria, para salvaguardar la protección del acceso libre e irrestricto de los ciudadanos a este Portal y a su información podrá adoptar medidas restrictivas de acceso al API ante situaciones de manifiesto abuso del servicio, riesgos de seguridad, o uso fraudulento de la información descargada, de acuerdo con las buenas prácticas de gestión de datos abiertos (https://datos.gob.es/es/blog/limitaciones-la-consulta-de-una-api) establecidas por el Ministerio para la Transformación Digital y de la Función Pública."
}