{"id":1113382,"organo":{"nivel1":"LOCAL","nivel2":"CAMPO DE CRIPTANA","nivel3":"AYUNTAMIENTO DE CAMPO DE CRIPTANA"},"sedeElectronica":null,"codigoBDNS":"911821","fechaRecepcion":"2026-06-10","instrumentos":[{"descripcion":"SUBVENCIÓN Y ENTREGA DINERARIA SIN CONTRAPRESTACIÓN "}],"tipoConvocatoria":"Concurrencia competitiva - canónica","presupuestoTotal":5000,"mrr":false,"descripcion":"Convocatoria de ayudas sociales para el estudio Fernando Villanueva Ruiz","descripcionLeng":null,"tiposBeneficiarios":[{"descripcion":"PERSONAS FÍSICAS QUE NO DESARROLLAN ACTIVIDAD ECONÓMICA"}],"sectores":[{"descripcion":"ACTIVIDADES ARTÍSTICAS, DEPORTIVAS Y DE ENTRETENIMIENTO","codigo":"S"},{"descripcion":"EDUCACIÓN","codigo":"Q"}],"regiones":[{"descripcion":"ES422 - Ciudad Real"}],"descripcionFinalidad":"Educación","descripcionBasesReguladoras":"Resolución de Alcaldía 924/2026 de fecha 21 de mayo de 2026 por la que se convocan las ayudas sociales para el estudio Fernando Villanueva Ruiz","urlBasesReguladoras":"https://campodecriptana.sedelectronica.es/preview-document/e2a93bce-c24a-4981-8d5d-93a4c97f14fd/","sePublicaDiarioOficial":true,"abierto":false,"fechaInicioSolicitud":null,"fechaFinSolicitud":null,"textInicio":"Desde el día siguiente a la publicación del extracto de la convocatoria en el BOP ","textFin":"30 días hábiles desde el día siguiente de la publicación del extracto de la convocatoria en el BOP","ayudaEstado":null,"urlAyudaEstado":null,"fondos":[],"reglamento":null,"objetivos":[],"sectoresProductos":[],"documentos":[{"id":1472654,"descripcion":"Documento de la convocatoria en español","nombreFic":"20260522_Publicación_Bases Becas Fernando Villanueva Ruiz convocatoria 2026 (2).pdf","long":377034,"datMod":"2026-06-10","datPublicacion":"2026-06-10"},{"id":1472656,"descripcion":"Modelo Cuenta Justificativa","nombreFic":"20260512_Otros_MODELO CUENTA JUSTIFICATIVA Becas Fdo. Villanueva Ruiz Conv. 2026.docx","long":373410,"datMod":"2026-06-10","datPublicacion":"2026-06-10"},{"id":1472655,"descripcion":"Solicitud","nombreFic":"20260522_Otros_ANEXO I SOLICITUD Becas Fdo.Vva.Ruiz - CONV.2026.docx","long":385483,"datMod":"2026-06-10","datPublicacion":"2026-06-10"}],"anuncios":[],"advertencia":"La reutilización de los datos del Sistema Nacional de Publicidad de Subvenciones y Ayudas Públicas está sujeta a una serie de restricciones y consideraciones legales. Consulte el aviso legal en https://www.infosubvenciones.es/bdnstrans/GE/es/avisolegal.Además, el usuario debe ser consciente que la información presentada es de naturaleza dinámica, y que los datos pueden ser sometidos a correcciones, inserciones, modificaciones y eliminaciones en momentos posteriores a su extracción. Accesos al API del sistema Nacional de Publicidad de Subvenciones y Ayudas Públicas. La Administración Presupuestaria, para salvaguardar la protección del acceso libre e irrestricto de los ciudadanos a este Portal y a su información podrá adoptar medidas restrictivas de acceso al API ante situaciones de manifiesto abuso del servicio, riesgos de seguridad, o uso fraudulento de la información descargada, de acuerdo con las buenas prácticas de gestión de datos abiertos (https://datos.gob.es/es/blog/limitaciones-la-consulta-de-una-api) establecidas por el Ministerio para la Transformación Digital y de la Función Pública."}